docs/Makefile
docs/make.bat
docs/requirements.txt
docs/source/README.md
docs/source/callbacks.rst
docs/source/conf.py
docs/source/dataset.rst
docs/source/index.rst
docs/source/models.rst
docs/source/modules.rst
docs/source/optuna_models.rst
docs/source/readme.rst
docs/source/utils.rst
escapydl/Callbacks.py
escapydl/Dataset.py
escapydl/Models.py
escapydl/Optuna_models.py
escapydl/Utils.py
escapydl/__version__.py
escapydl/gui.py
escapydl/main.py
escapydl/optimize.py
escapydl/train.py
escapydl/datasets/aesrd.py
escapydl/datasets/ascad_fixed.py
escapydl/datasets/ascad_random.py
escapydl/datasets/ascon.py
escapydl/datasets/ascon_multi_sbox.py
escapydl/datasets/ascon_sbox.py
escapydl/datasets/ascon_sbox_8bit.py
escapydl/datasets/ascon_sbox_chunk.py
escapydl/datasets/asconp2.py
escapydl/datasets/dpav4.py
escapydl/datasets/dpav4_multi.py
escapydl/datasets/dpav4_n.py
escapydl/datasets/to_json.py
escapydl/helpers/aes_helper.py
escapydl/helpers/ascon_helper.py
escapydl/helpers/xoodyak_helper.py
escapydl/resources/resource.gresource
escapydl/resources/resource.gresource.xml
escapydl/resources/org/gnome/escapydl/icons/128x128/apps/escapydl-icon.png
escapydl/resources/org/gnome/escapydl/icons/64x64/apps/escapydl-icon.png
escapydl/resources/org/gnome/escapydl/icons/scalable/apps/escapydl-icon.svg
escapydl/resources/org/gnome/escapydl/themes/dark-theme.css
tests/test_callbacks.py
tests/test_datasets.py
tests/test_models.py
tests/test_optuna_models.py
tests/test_utils.py
venv/bin/activate_this.py
venv/bin/bottle.py
venv/bin/rst2html.py
venv/bin/rst2html4.py
venv/bin/rst2html5.py
venv/bin/rst2latex.py
venv/bin/rst2man.py
venv/bin/rst2odt.py
venv/bin/rst2odt_prepstyles.py
venv/bin/rst2pseudoxml.py
venv/bin/rst2s5.py
venv/bin/rst2xetex.py
venv/bin/rst2xml.py
venv/bin/rstpep2html.py
escapydl-0.0.9.dist-info/LICENSE
escapydl-0.0.9.dist-info/METADATA
escapydl-0.0.9.dist-info/WHEEL
escapydl-0.0.9.dist-info/entry_points.txt
escapydl-0.0.9.dist-info/top_level.txt
escapydl-0.0.9.dist-info/RECORD
