Metadata-Version: 2.1
Name: escapydl
Version: 0.0.9
Summary: A Deep Learning framework for Side-channel Analysis in PyTorch
Author-email: Léo Weissbart <l.weissbart@proton.me>
Project-URL: repository, https://gitlab.com/leo_w/escapydl
Project-URL: documentation, https://leo_w.gitlab.io/escapydl
Classifier: Programming Language :: Python :: 3
Classifier: License :: OSI Approved :: GNU General Public License v3 (GPLv3)
Classifier: Operating System :: OS Independent
Classifier: Environment :: X11 Applications :: GTK
Requires-Python: >=3.10
License-File: LICENSE
Requires-Dist: requests
Requires-Dist: torch
Requires-Dist: numpy
Requires-Dist: matplotlib
Requires-Dist: tensorboard
Requires-Dist: optuna
Requires-Dist: optuna-dashboard
Requires-Dist: progressbar2
Requires-Dist: trsfile
Requires-Dist: h5py
Requires-Dist: PyGObject
Requires-Dist: SQLAlchemy
Requires-Dist: importlib-metadata ; python_version >= "3.10"
